{
 "cells": [
  {
   "cell_type": "code",
   "execution_count": 1,
   "metadata": {},
   "outputs": [],
   "source": [
    "import numpy as np\n",
    "import torch\n",
    "\n",
    "##Per i grafici 3d indagare plotly\n",
    "from kymatio.torch import HarmonicScattering3D\n",
    "from kymatio.scattering3d.backend.torch_backend \\\n",
    "    import TorchBackend3D\n",
    "\n",
    "# Reads Quijote halo catalogues\n",
    "import readfof"
   ]
  },
  {
   "cell_type": "markdown",
   "metadata": {},
   "source": [
    "import sys\n",
    "sys.path.insert(1, '/home/fuffolo97/TESI/MyFunc')\n",
    "from CalcWST import HaloWST"
   ]
  },
  {
   "attachments": {},
   "cell_type": "markdown",
   "metadata": {},
   "source": [
    "I cataloghi di aloni sono elenchi degli aloni presi come punti massivi\n",
    "\n",
    "Ognuno ha una propria massa e un numero di particelle di CDM da cui è formato"
   ]
  },
  {
   "cell_type": "code",
   "execution_count": 2,
   "metadata": {},
   "outputs": [],
   "source": [
    "# input file\n",
    "# need to select a folder and there must be\n",
    "# a folder named '/groups_00*snapnum*'\n",
    "snapdir = '/home/fuffolo97/TESI/Try_02-HaloCatalogue/Halos/fiducial/1'\n",
    "snapnum = 2\n",
    "\n",
    "# determine the reìdshift of the catalogue\n",
    "z_dict = {4:0.0, 3:0.5, 2:1.0, 1:2.0, 0:3.0}\n",
    "redshift = z_dict[snapnum]"
   ]
  },
  {
   "cell_type": "code",
   "execution_count": 3,
   "metadata": {},
   "outputs": [],
   "source": [
    "# read the halo catalogue\n",
    "datas = readfof.FoF_catalog(snapdir, snapnum, read_IDs=False)"
   ]
  },
  {
   "cell_type": "code",
   "execution_count": 4,
   "metadata": {},
   "outputs": [],
   "source": [
    "# how to get the propeties of the halos\n",
    "pos_h = datas.GroupPos/1e3              # positions in Mpc/h\n",
    "mass = datas.GroupMass * 1e10           # masses in M_sun/h\n",
    "# vel_h = datas.GroupVel * (1.0*redshift) # peculiar velocities in km/s\n",
    "# Npart = datas.GroupLen                  # number of CDM particles in the halo"
   ]
  },
  {
   "attachments": {},
   "cell_type": "markdown",
   "metadata": {},
   "source": [
    "#### Create density matrix from Quijote Halo simulation"
   ]
  },
  {
   "cell_type": "code",
   "execution_count": 6,
   "metadata": {},
   "outputs": [],
   "source": [
    "import sys\n",
    "\n",
    "sys.path.insert(1, '../MyFunc')\n",
    "from myCIC import cic, miafunzione"
   ]
  },
  {
   "cell_type": "code",
   "execution_count": 6,
   "metadata": {},
   "outputs": [],
   "source": [
    "# import cProfile\n",
    "# cProfile.run('dens = cic(pos_h, mass, 128, 1000)', \"results.prof\")\n",
    "\n",
    "#dens = cic_multiT(pos_h, mass, 128)"
   ]
  },
  {
   "attachments": {},
   "cell_type": "markdown",
   "metadata": {},
   "source": [
    "CIC non multithread:\n",
    "- Before for loops:  0.008156299591064453 s \n",
    "- For loops:  135.50461220741272 s\n",
    "- TOT $\\sim$ 2m 15s\n",
    "\n",
    "CIC non multithread (inverted for loops): same\n",
    "\n",
    "CIC using function inside 'for i in ...':\n",
    "- TOT $\\sim$ 2m 11s\n",
    "\n",
    "CIC movingcheck of boundaries before 'for x in range...'\n",
    "- 1m 15s\n",
    "\n",
    "CIC calculating before 'forx in range...' CELL[0], CELL[1],...:\n",
    "- 1m 7s"
   ]
  },
  {
   "cell_type": "code",
   "execution_count": 7,
   "metadata": {},
   "outputs": [],
   "source": [
    "dens2 = cic(pos_h, mass, 128)"
   ]
  },
  {
   "cell_type": "code",
   "execution_count": 8,
   "metadata": {},
   "outputs": [],
   "source": [
    "# %load_ext snakeviz"
   ]
  },
  {
   "cell_type": "markdown",
   "metadata": {},
   "source": [
    "time: 3m 7.1s"
   ]
  },
  {
   "attachments": {},
   "cell_type": "markdown",
   "metadata": {},
   "source": [
    "#### Calculate scattering transform coefficients"
   ]
  },
  {
   "cell_type": "code",
   "execution_count": 9,
   "metadata": {},
   "outputs": [],
   "source": [
    "# parameters for HarmonicScattering3D\n",
    "M, N, O = 128, 128, 128\n",
    "J, L = 4, 4"
   ]
  },
  {
   "cell_type": "code",
   "execution_count": 10,
   "metadata": {},
   "outputs": [],
   "source": [
    "S = HarmonicScattering3D(J=J, L=L, shape=(M, N, O), sigma_0=0.8, integral_powers=[0.8])"
   ]
  },
  {
   "cell_type": "code",
   "execution_count": 11,
   "metadata": {},
   "outputs": [],
   "source": [
    "# argument of \"torch.from_numpy(...)\" must be numpy.float32()\n",
    "Sx = S.scattering(torch.from_numpy(dens2))"
   ]
  },
  {
   "cell_type": "code",
   "execution_count": 12,
   "metadata": {},
   "outputs": [],
   "source": [
    "first_order = []\n",
    "second_order = []\n",
    "\n",
    "for i in range(L+1):\n",
    "    for j in range(J+1):\n",
    "        first_order.append(Sx[j, i, 0])\n",
    "    second_order.append(Sx[5:,i,0].numpy())"
   ]
  },
  {
   "cell_type": "code",
   "execution_count": 13,
   "metadata": {},
   "outputs": [
    {
     "name": "stdout",
     "output_type": "stream",
     "text": [
      "193           0 LOAD_GLOBAL              0 (np)\n",
      "              2 LOAD_METHOD              1 (zeros)\n",
      "              4 LOAD_CONST               1 ((2, 2, 2))\n",
      "              6 CALL_METHOD              1\n",
      "              8 STORE_FAST               7 (cube)\n",
      "\n",
      "194          10 LOAD_FAST                6 (vecs)\n",
      "             12 GET_ITER\n",
      "        >>   14 FOR_ITER                34 (to 84)\n",
      "             16 STORE_FAST               8 (v)\n",
      "\n",
      "195          18 LOAD_FAST                7 (cube)\n",
      "             20 LOAD_FAST                8 (v)\n",
      "             22 LOAD_CONST               2 (0)\n",
      "             24 BINARY_SUBSCR\n",
      "             26 BINARY_SUBSCR\n",
      "             28 LOAD_FAST                8 (v)\n",
      "             30 LOAD_CONST               3 (1)\n",
      "             32 BINARY_SUBSCR\n",
      "             34 BINARY_SUBSCR\n",
      "             36 LOAD_FAST                8 (v)\n",
      "             38 LOAD_CONST               4 (2)\n",
      "             40 BINARY_SUBSCR\n",
      "             42 DUP_TOP_TWO\n",
      "             44 BINARY_SUBSCR\n",
      "             46 LOAD_FAST                0 (m)\n",
      "             48 LOAD_GLOBAL              0 (np)\n",
      "             50 LOAD_METHOD              2 (abs)\n",
      "             52 LOAD_GLOBAL              0 (np)\n",
      "             54 LOAD_METHOD              3 (prod)\n",
      "             56 LOAD_CONST               3 (1)\n",
      "             58 LOAD_FAST                8 (v)\n",
      "             60 BINARY_SUBTRACT\n",
      "             62 LOAD_FAST                2 (step)\n",
      "             64 BINARY_MULTIPLY\n",
      "             66 LOAD_FAST                5 (DIST)\n",
      "             68 BINARY_SUBTRACT\n",
      "             70 CALL_METHOD              1\n",
      "             72 CALL_METHOD              1\n",
      "             74 BINARY_MULTIPLY\n",
      "             76 INPLACE_ADD\n",
      "             78 ROT_THREE\n",
      "             80 STORE_SUBSCR\n",
      "             82 JUMP_ABSOLUTE            7 (to 14)\n",
      "\n",
      "197     >>   84 LOAD_CONST               5 ((0, 1))\n",
      "             86 GET_ITER\n",
      "        >>   88 FOR_ITER               221 (to 532)\n",
      "             90 STORE_FAST               9 (a)\n",
      "\n",
      "198          92 LOAD_CONST               5 ((0, 1))\n",
      "             94 GET_ITER\n",
      "        >>   96 FOR_ITER               216 (to 530)\n",
      "             98 STORE_FAST              10 (b)\n",
      "\n",
      "199         100 LOAD_CONST               5 ((0, 1))\n",
      "            102 GET_ITER\n",
      "        >>  104 FOR_ITER               211 (to 528)\n",
      "            106 STORE_FAST              11 (c)\n",
      "\n",
      "200         108 LOAD_GLOBAL              0 (np)\n",
      "            110 LOAD_METHOD              4 (where)\n",
      "            112 LOAD_FAST                4 (CELL)\n",
      "            114 LOAD_FAST                9 (a)\n",
      "            116 LOAD_FAST               10 (b)\n",
      "            118 LOAD_FAST               11 (c)\n",
      "            120 BUILD_LIST               3\n",
      "            122 BINARY_ADD\n",
      "            124 LOAD_FAST                1 (N_grid)\n",
      "            126 COMPARE_OP               2 (==)\n",
      "            128 CALL_METHOD              1\n",
      "            130 LOAD_CONST               2 (0)\n",
      "            132 BINARY_SUBSCR\n",
      "            134 GET_ITER\n",
      "        >>  136 FOR_ITER                 6 (to 150)\n",
      "            138 STORE_FAST              12 (l)\n",
      "\n",
      "201         140 LOAD_CONST               6 (-1)\n",
      "            142 LOAD_FAST                4 (CELL)\n",
      "            144 LOAD_FAST               12 (l)\n",
      "            146 STORE_SUBSCR\n",
      "            148 JUMP_ABSOLUTE           68 (to 136)\n",
      "\n",
      "203     >>  150 LOAD_FAST                7 (cube)\n",
      "            152 LOAD_FAST                9 (a)\n",
      "            154 BINARY_SUBSCR\n",
      "            156 LOAD_FAST               10 (b)\n",
      "            158 BINARY_SUBSCR\n",
      "            160 LOAD_FAST               11 (c)\n",
      "            162 BINARY_SUBSCR\n",
      "            164 STORE_FAST              13 (cubo)\n",
      "\n",
      "204         166 LOAD_FAST                4 (CELL)\n",
      "            168 LOAD_CONST               2 (0)\n",
      "            170 BINARY_SUBSCR\n",
      "            172 STORE_FAST              14 (cell0)\n",
      "\n",
      "205         174 LOAD_FAST                4 (CELL)\n",
      "            176 LOAD_CONST               3 (1)\n",
      "            178 BINARY_SUBSCR\n",
      "            180 STORE_FAST              15 (cell1)\n",
      "\n",
      "206         182 LOAD_FAST                4 (CELL)\n",
      "            184 LOAD_CONST               4 (2)\n",
      "            186 BINARY_SUBSCR\n",
      "            188 STORE_FAST              16 (cell2)\n",
      "\n",
      "208         190 LOAD_FAST                3 (density)\n",
      "            192 LOAD_FAST               14 (cell0)\n",
      "            194 LOAD_FAST                9 (a)\n",
      "            196 BINARY_ADD\n",
      "            198 BINARY_SUBSCR\n",
      "            200 LOAD_FAST               15 (cell1)\n",
      "            202 LOAD_FAST               10 (b)\n",
      "            204 BINARY_ADD\n",
      "            206 BINARY_SUBSCR\n",
      "            208 LOAD_FAST               16 (cell2)\n",
      "            210 LOAD_FAST               11 (c)\n",
      "            212 BINARY_ADD\n",
      "            214 LOAD_CONST               3 (1)\n",
      "            216 BINARY_SUBTRACT\n",
      "            218 DUP_TOP_TWO\n",
      "            220 BINARY_SUBSCR\n",
      "            222 LOAD_FAST               13 (cubo)\n",
      "            224 INPLACE_ADD\n",
      "            226 ROT_THREE\n",
      "            228 STORE_SUBSCR\n",
      "\n",
      "209         230 LOAD_FAST                3 (density)\n",
      "            232 LOAD_FAST               14 (cell0)\n",
      "            234 LOAD_FAST                9 (a)\n",
      "            236 BINARY_ADD\n",
      "            238 BINARY_SUBSCR\n",
      "            240 LOAD_FAST               15 (cell1)\n",
      "            242 LOAD_FAST               10 (b)\n",
      "            244 BINARY_ADD\n",
      "            246 BINARY_SUBSCR\n",
      "            248 LOAD_FAST               16 (cell2)\n",
      "            250 LOAD_FAST               11 (c)\n",
      "            252 BINARY_ADD\n",
      "            254 DUP_TOP_TWO\n",
      "            256 BINARY_SUBSCR\n",
      "            258 LOAD_FAST               13 (cubo)\n",
      "            260 INPLACE_ADD\n",
      "            262 ROT_THREE\n",
      "            264 STORE_SUBSCR\n",
      "\n",
      "210         266 LOAD_FAST                3 (density)\n",
      "            268 LOAD_FAST               14 (cell0)\n",
      "            270 LOAD_FAST                9 (a)\n",
      "            272 BINARY_ADD\n",
      "            274 BINARY_SUBSCR\n",
      "            276 LOAD_FAST               15 (cell1)\n",
      "            278 LOAD_FAST               10 (b)\n",
      "            280 BINARY_ADD\n",
      "            282 LOAD_CONST               3 (1)\n",
      "            284 BINARY_SUBTRACT\n",
      "            286 BINARY_SUBSCR\n",
      "            288 LOAD_FAST               16 (cell2)\n",
      "            290 LOAD_FAST               11 (c)\n",
      "            292 BINARY_ADD\n",
      "            294 LOAD_CONST               3 (1)\n",
      "            296 BINARY_SUBTRACT\n",
      "            298 DUP_TOP_TWO\n",
      "            300 BINARY_SUBSCR\n",
      "            302 LOAD_FAST               13 (cubo)\n",
      "            304 INPLACE_ADD\n",
      "            306 ROT_THREE\n",
      "            308 STORE_SUBSCR\n",
      "\n",
      "211         310 LOAD_FAST                3 (density)\n",
      "            312 LOAD_FAST               14 (cell0)\n",
      "            314 LOAD_FAST                9 (a)\n",
      "            316 BINARY_ADD\n",
      "            318 BINARY_SUBSCR\n",
      "            320 LOAD_FAST               15 (cell1)\n",
      "            322 LOAD_FAST               10 (b)\n",
      "            324 BINARY_ADD\n",
      "            326 LOAD_CONST               3 (1)\n",
      "            328 BINARY_SUBTRACT\n",
      "            330 BINARY_SUBSCR\n",
      "            332 LOAD_FAST               16 (cell2)\n",
      "            334 LOAD_FAST               11 (c)\n",
      "            336 BINARY_ADD\n",
      "            338 DUP_TOP_TWO\n",
      "            340 BINARY_SUBSCR\n",
      "            342 LOAD_FAST               13 (cubo)\n",
      "            344 INPLACE_ADD\n",
      "            346 ROT_THREE\n",
      "            348 STORE_SUBSCR\n",
      "\n",
      "212         350 LOAD_FAST                3 (density)\n",
      "            352 LOAD_FAST               14 (cell0)\n",
      "            354 LOAD_FAST                9 (a)\n",
      "            356 BINARY_ADD\n",
      "            358 LOAD_CONST               3 (1)\n",
      "            360 BINARY_SUBTRACT\n",
      "            362 BINARY_SUBSCR\n",
      "            364 LOAD_FAST               15 (cell1)\n",
      "            366 LOAD_FAST               10 (b)\n",
      "            368 BINARY_ADD\n",
      "            370 BINARY_SUBSCR\n",
      "            372 LOAD_FAST               16 (cell2)\n",
      "            374 LOAD_FAST               11 (c)\n",
      "            376 BINARY_ADD\n",
      "            378 LOAD_CONST               3 (1)\n",
      "            380 BINARY_SUBTRACT\n",
      "            382 DUP_TOP_TWO\n",
      "            384 BINARY_SUBSCR\n",
      "            386 LOAD_FAST               13 (cubo)\n",
      "            388 INPLACE_ADD\n",
      "            390 ROT_THREE\n",
      "            392 STORE_SUBSCR\n",
      "\n",
      "213         394 LOAD_FAST                3 (density)\n",
      "            396 LOAD_FAST               14 (cell0)\n",
      "            398 LOAD_FAST                9 (a)\n",
      "            400 BINARY_ADD\n",
      "            402 LOAD_CONST               3 (1)\n",
      "            404 BINARY_SUBTRACT\n",
      "            406 BINARY_SUBSCR\n",
      "            408 LOAD_FAST               15 (cell1)\n",
      "            410 LOAD_FAST               10 (b)\n",
      "            412 BINARY_ADD\n",
      "            414 BINARY_SUBSCR\n",
      "            416 LOAD_FAST               16 (cell2)\n",
      "            418 LOAD_FAST               11 (c)\n",
      "            420 BINARY_ADD\n",
      "            422 DUP_TOP_TWO\n",
      "            424 BINARY_SUBSCR\n",
      "            426 LOAD_FAST               13 (cubo)\n",
      "            428 INPLACE_ADD\n",
      "            430 ROT_THREE\n",
      "            432 STORE_SUBSCR\n",
      "\n",
      "214         434 LOAD_FAST                3 (density)\n",
      "            436 LOAD_FAST               14 (cell0)\n",
      "            438 LOAD_FAST                9 (a)\n",
      "            440 BINARY_ADD\n",
      "            442 LOAD_CONST               3 (1)\n",
      "            444 BINARY_SUBTRACT\n",
      "            446 BINARY_SUBSCR\n",
      "            448 LOAD_FAST               15 (cell1)\n",
      "            450 LOAD_FAST               10 (b)\n",
      "            452 BINARY_ADD\n",
      "            454 LOAD_CONST               3 (1)\n",
      "            456 BINARY_SUBTRACT\n",
      "            458 BINARY_SUBSCR\n",
      "            460 LOAD_FAST               16 (cell2)\n",
      "            462 LOAD_FAST               11 (c)\n",
      "            464 BINARY_ADD\n",
      "            466 LOAD_CONST               3 (1)\n",
      "            468 BINARY_SUBTRACT\n",
      "            470 DUP_TOP_TWO\n",
      "            472 BINARY_SUBSCR\n",
      "            474 LOAD_FAST               13 (cubo)\n",
      "            476 INPLACE_ADD\n",
      "            478 ROT_THREE\n",
      "            480 STORE_SUBSCR\n",
      "\n",
      "215         482 LOAD_FAST                3 (density)\n",
      "            484 LOAD_FAST               14 (cell0)\n",
      "            486 LOAD_FAST                9 (a)\n",
      "            488 BINARY_ADD\n",
      "            490 LOAD_CONST               3 (1)\n",
      "            492 BINARY_SUBTRACT\n",
      "            494 BINARY_SUBSCR\n",
      "            496 LOAD_FAST               15 (cell1)\n",
      "            498 LOAD_FAST               10 (b)\n",
      "            500 BINARY_ADD\n",
      "            502 LOAD_CONST               3 (1)\n",
      "            504 BINARY_SUBTRACT\n",
      "            506 BINARY_SUBSCR\n",
      "            508 LOAD_FAST               16 (cell2)\n",
      "            510 LOAD_FAST               11 (c)\n",
      "            512 BINARY_ADD\n",
      "            514 DUP_TOP_TWO\n",
      "            516 BINARY_SUBSCR\n",
      "            518 LOAD_FAST               13 (cubo)\n",
      "            520 INPLACE_ADD\n",
      "            522 ROT_THREE\n",
      "            524 STORE_SUBSCR\n",
      "            526 JUMP_ABSOLUTE           52 (to 104)\n",
      "\n",
      "199     >>  528 JUMP_ABSOLUTE           48 (to 96)\n",
      "\n",
      "198     >>  530 JUMP_ABSOLUTE           44 (to 88)\n",
      "\n",
      "197     >>  532 LOAD_CONST               0 (None)\n",
      "            534 RETURN_VALUE\n"
     ]
    }
   ],
   "source": [
    "import dis\n",
    "\n",
    "dis.dis(miafunzione1)"
   ]
  },
  {
   "attachments": {},
   "cell_type": "markdown",
   "metadata": {},
   "source": [
    "All the previous calcs can be done now simply by:\n",
    "\n",
    "```\n",
    "$ import sys\n",
    "$ sys.path.insert(1, '/home/fuffolo97/TESI/MyFunc')\n",
    "$ from CalcWST import HaloWST\n",
    "$ snapdir = '/path/to/files/without/groups_'\n",
    "$ WST = HaloWST(snapdir)\n",
    "```"
   ]
  }
 ],
 "metadata": {
  "kernelspec": {
   "display_name": "venv",
   "language": "python",
   "name": "python3"
  },
  "language_info": {
   "codemirror_mode": {
    "name": "ipython",
    "version": 3
   },
   "file_extension": ".py",
   "mimetype": "text/x-python",
   "name": "python",
   "nbconvert_exporter": "python",
   "pygments_lexer": "ipython3",
   "version": "3.10.4"
  },
  "orig_nbformat": 4,
  "vscode": {
   "interpreter": {
    "hash": "432bbbb1169051df795428fc481fe68f2019ca6cb67b62b2f37893fa604d8822"
   }
  }
 },
 "nbformat": 4,
 "nbformat_minor": 2
}
